pygong/__init__.py
pygong/common_log.py
pygong/common_unit.py
pygong/io_fcntl.py
pygong/pygong.VERSION
pygong-0.0.3.dist-info/LICENSE
pygong-0.0.3.dist-info/METADATA
pygong-0.0.3.dist-info/WHEEL
pygong-0.0.3.dist-info/top_level.txt
pygong-0.0.3.dist-info/RECORD
