Metadata-Version: 2.1
Name: pygong
Version: 0.0.3
Summary: Supported for python dev common utils collection library.
Author-email: gongwendong <gwd163nom@163.com>
Maintainer-email: gongwendong <gwd163nom@163.com>
License: Apache License
Project-URL: Homepage, https://github.com/agodomen/pygong
Project-URL: Documentation, https://github.com/agodomen/pygong/blob/main/README_ZH.md
Project-URL: Repository, https://github.com/agodomen/pygong.git
Project-URL: Issues, https://github.com/agodomen/pygong/issues
Project-URL: Changelog, https://github.com/agodomen/pygong/blob/main/CHANGELOG.md
Keywords: python utils,python common
Classifier: Programming Language :: Python :: 3
Classifier: License :: OSI Approved :: Apache Software License
Classifier: Operating System :: OS Independent
Requires-Python: >=3.1
License-File: LICENSE
Requires-Dist: pint
